HowdenPipeline/__init__.py
HowdenPipeline/flow/file_pipeline_runner.py
HowdenPipeline/flow/graph_pipeline.py
HowdenPipeline/flow/match.py
HowdenPipeline/flow/parameter_serializer.py
HowdenPipeline/flow/pipeline_graph_manager.py
HowdenPipeline/flow/step_hasher.py
HowdenPipeline/flow/step_namer.py
HowdenPipeline/manager/jsonMatcher.py
howdenpipeline-3.1.0.dist-info/METADATA
howdenpipeline-3.1.0.dist-info/WHEEL
howdenpipeline-3.1.0.dist-info/RECORD
