Metadata-Version: 2.4
Name: HowdenPipeline
Version: 3.1.0
Summary: A simple configuration manager with Pydantic and JSON export.
License: MIT
Keywords: config,configuration,pydantic,json
Author: JesperThoftIllemannJ
Author-email: jesper.jaeger@howdendanmark.dk
Requires-Python: >=3.12,<3.14
Classifier: License :: OSI Approved :: MIT License
Classifier: Programming Language :: Python :: 3
Classifier: Programming Language :: Python :: 3.12
Classifier: Programming Language :: Python :: 3.13
Requires-Dist: gradio (>=5.49.1,<6.0.0)
Requires-Dist: graphviz (>=0.21,<0.22)
Requires-Dist: howdenconfig (>=1.0.6,<2.0.0)
Requires-Dist: howdenllm (>=1.1.10)
Requires-Dist: howdenparser (>=5.2.1)
Requires-Dist: pytest (>=9.0.2,<10.0.0)
Requires-Dist: uvicorn (==0.25.0)
Project-URL: Documentation, https://github.com/yourusername/config
Project-URL: Homepage, https://github.com/yourusername/config
Project-URL: Repository, https://github.com/yourusername/config
